odoo/addons/account_invoice_auto_send_by_email/README.rst
odoo/addons/account_invoice_auto_send_by_email/__init__.py
odoo/addons/account_invoice_auto_send_by_email/__manifest__.py
odoo/addons/account_invoice_auto_send_by_email/data/ir_cron.xml
odoo/addons/account_invoice_auto_send_by_email/i18n/account_invoice_auto_send_by_email.pot
odoo/addons/account_invoice_auto_send_by_email/i18n/it.po
odoo/addons/account_invoice_auto_send_by_email/models/__init__.py
odoo/addons/account_invoice_auto_send_by_email/models/account_move.py
odoo/addons/account_invoice_auto_send_by_email/readme/CONTRIBUTORS.rst
odoo/addons/account_invoice_auto_send_by_email/readme/DESCRIPTION.rst
odoo/addons/account_invoice_auto_send_by_email/static/description/icon.png
odoo/addons/account_invoice_auto_send_by_email/static/description/index.html
odoo/addons/account_invoice_auto_send_by_email/tests/__init__.py
odoo/addons/account_invoice_auto_send_by_email/tests/test_account_invoice_auto_send_by_email.py
odoo14_addon_account_invoice_auto_send_by_email-14.0.1.0.1.dist-info/METADATA
odoo14_addon_account_invoice_auto_send_by_email-14.0.1.0.1.dist-info/WHEEL
odoo14_addon_account_invoice_auto_send_by_email-14.0.1.0.1.dist-info/top_level.txt
odoo14_addon_account_invoice_auto_send_by_email-14.0.1.0.1.dist-info/RECORD
